tentaclio_s3/__init__.py
tentaclio_s3/__main__.py
tentaclio_s3/clients/__init__.py
tentaclio_s3/clients/exceptions.py
tentaclio_s3/clients/s3_client.py
tentaclio_s3-0.0.3.dist-info/LICENSE.txt
tentaclio_s3-0.0.3.dist-info/METADATA
tentaclio_s3-0.0.3.dist-info/WHEEL
tentaclio_s3-0.0.3.dist-info/top_level.txt
tentaclio_s3-0.0.3.dist-info/RECORD
