Metadata-Version: 2.1
Name: tentaclio-s3
Version: 0.0.3
Summary: A python project containing all the dependencies for schema s3 for tentaclio.
Author: Octopus Energy
Author-email: nerds@octopus.energy
License: Proprietary
Classifier: Intended Audience :: Developers
Classifier: Operating System :: OS Independent
Classifier: Programming Language :: Python
Classifier: Programming Language :: Python :: 3
Classifier: Programming Language :: Python :: 3.6
Classifier: Programming Language :: Python :: 3.7
Classifier: Programming Language :: Python :: 3.8
Classifier: Programming Language :: Python :: 3.9
License-File: LICENSE.txt
Requires-Dist: tentaclio
Requires-Dist: boto3
